samba/__init__.py
samba/fva/__init__.py
samba/fva/fva_functions.py
samba/iopy/__init__.py
samba/iopy/export.py
samba/iopy/read_model.py
samba/sampling/__init__.py
samba/sampling/sample_functions.py
samba/sampling/wtopt.py
samba/setup/__init__.py
samba/setup/prepare_reactions.py
sambaflux-0.2.2.dist-info/LICENSE
sambaflux-0.2.2.dist-info/METADATA
sambaflux-0.2.2.dist-info/WHEEL
sambaflux-0.2.2.dist-info/top_level.txt
sambaflux-0.2.2.dist-info/RECORD
