Metadata-Version: 2.1
Name: sambaflux
Version: 0.2.2
Summary: Sampling Biomarker Analysis using flux sampling
Home-page: https://forgemia.inra.fr/metexplore/cbm/samba/-/tree/main/sambaflux
Author: Juliette Cooke
Author-email: juliette.cooke@inrae.fr
Project-URL: Bug Tracker, https://forgemia.inra.fr/metexplore/cbm/samba/-/issues
Classifier: Programming Language :: Python :: 3
Classifier: License :: OSI Approved :: MIT License
Classifier: Operating System :: Unix
Requires-Python: >=3.6
License-File: LICENSE
Requires-Dist: cobra >=0.24.0
